TurboTest/__init__.py
TurboTest/__main__.py
TurboTest/constants.py
TurboTest/core/__init__.py
TurboTest/core/chemicals/__init__.py
TurboTest/core/chemicals/test.py
TurboTest/core/chemicals/both_are_equal/__init__.py
TurboTest/core/chemicals/both_are_equal/test.py
TurboTest/core/chemicals/the_string_matches_the_regex/__init__.py
TurboTest/core/chemicals/the_string_matches_the_regex/test.py
TurboTest/core/chemicals/these_two_must_be_different/__init__.py
TurboTest/core/chemicals/these_two_must_be_different/test.py
TurboTest/core/chemicals/these_will_raise/__init__.py
TurboTest/core/chemicals/these_will_raise/test.py
TurboTest/core/chemicals/this_is_False/__init__.py
TurboTest/core/chemicals/this_is_False/test.py
TurboTest/core/chemicals/this_is_True/__init__.py
TurboTest/core/chemicals/this_is_True/test.py
TurboTest/core/error_tt/__init__.py
TurboTest/core/error_tt/test.py
TurboTest/runner/__init__.py
TurboTest/runner/test.py
TurboTest/runner/concluder/__init__.py
TurboTest/runner/is_tt_test_file/__init__.py
TurboTest/runner/is_tt_test_file/test.py
TurboTest/runner/is_tt_test_file/test_data/foo.py
TurboTest/runner/is_tt_test_file/test_data/test.py
TurboTest/runner/is_tt_test_file/test_data2/bar.py
TurboTest/runner/is_tt_test_file/test_data2/test.py
TurboTest/runner/printer/print_footer/__init__.py
TurboTest/runner/printer/print_header/__init__.py
TurboTest/runner/runtime_guard/__init__.py
TurboTest-0.15.0b0.dist-info/LICENSE
TurboTest-0.15.0b0.dist-info/METADATA
TurboTest-0.15.0b0.dist-info/WHEEL
TurboTest-0.15.0b0.dist-info/entry_points.txt
TurboTest-0.15.0b0.dist-info/top_level.txt
TurboTest-0.15.0b0.dist-info/RECORD
