Metadata-Version: 2.1
Name: TurboTest
Version: 0.15.0b0
Summary: a simple and readable python testing tool
Author-email: Nicholas Valentinus <nicho@scapeville.com>
License: MIT
Project-URL: Repository, https://github.com/nvfp/TurboTest
Requires-Python: >=3.8
License-File: LICENSE
